README.md
setup.py
wagner/__init__.py
wagner/wagner.py
wagner.egg-info/PKG-INFO
wagner.egg-info/SOURCES.txt
wagner.egg-info/dependency_links.txt
wagner.egg-info/top_level.txt