Metadata-Version: 1.1
Name: wagner
Version: 0.0.2
Summary: Python implementation of Wagner's Algorithm for the Generalized Birthday Problem.
Home-page: https://github.com/conduition/wagner
Author: conduition
Author-email: conduition@proton.me
License: UNKNOWN
Keywords: birthday,musig,attack,wagner,generalized birthday problem,k-sum,k sum
Platform: UNKNOWN
Classifier: Programming Language :: Python :: 3
Classifier: License :: OSI Approved :: The Unlicense (Unlicense)
Classifier: Operating System :: OS Independent
